greeter/__init__.py
greeter/greeter.py
greet_simple-0.1.0.dist-info/METADATA
greet_simple-0.1.0.dist-info/WHEEL
greet_simple-0.1.0.dist-info/top_level.txt
greet_simple-0.1.0.dist-info/RECORD
