Metadata-Version: 2.1
Name: greet-simple
Version: 0.1.0
Summary: A simple package for greeting people.
Author: Your Name
Author-email: your@email.com
Classifier: Programming Language :: Python :: 3
Classifier: License :: OSI Approved :: MIT License
Classifier: Operating System :: OS Independent
